<?xml version="1.0" encoding="UTF-8" ?>
<!DOCTYPE devices PUBLIC "-//YARP//DTD yarprobotinterface 3.0//EN" "http://www.yarp.it/DTD/yarprobotinterfaceV3.0.dtd">


    <device xmlns:xi="http://www.w3.org/2001/XInclude" name="iiwa-eb1-skin" type="embObjSkin">
        <xi:include href="../../general.xml" />
 
        <xi:include href="../../hardware/electronics/iiwa-eb1-skin-eln.xml" />

        <group name="SERVICE">
        
            <param name="type"> eomn_serv_SK_skin </param>

            <group name="PROPERTIES">
            
                <group name="CANBOARDS">
                    <param name="type">                 mtb4                 </param>
 
                    <group name="PROTOCOL">
                        <param name="major">            2                   </param>    
                        <param name="minor">            0                   </param>     
                    </group>                    
                    <group name="FIRMWARE">
                        <param name="major">            0                   </param>    
                        <param name="minor">            0                   </param> 
                        <param name="build">            0                   </param>
                    </group>
                </group>
           
            </group>  
        
        </group>  
   
        <group name="patches">
            <param name="skinCanAddrsPatch2">  1 2 3 4 5 6 7 8   </param> 
            <param name="skinCanAddrsPatch1">  9 10 11 12 13 14  </param> 
        </group>
        <xi:include href="./iiwa-eb1-skinSpec.xml" />
    </device>

  
