<?xml version="1.0" encoding="UTF-8" ?>
<!DOCTYPE params PUBLIC "-//YARP//DTD yarprobotinterface 3.0//EN" "http://www.yarp.it/DTD/yarprobotinterfaceV3.0.dtd">
 
<params xmlns:xi="http://www.w3.org/2001/XInclude" robot="iCubShanghai01" build="1">
    <group name="GENERAL">
        <param name="MotioncontrolVersion"> 6 </param>
        <param name="Joints"> 4 </param> <!-- the number of joints of the robot part -->

        <!-- joint number in sub-part           0                 1              2              3           -->
        <param name="AxisName">                 "r_wrist_prosup" "r_wrist_pitch" "r_wrist_yaw"  "r_hand_finger"  </param> 
        <param name="AxisType">                 "revolute"       "revolute"      "revolute"     "revolute"      </param>
        <param name="AxisMap">                  0                1               2              3               </param>   <!-- joint as effectively mapped onto the hw of the board -->
        <param name="Encoder">                  182.044          182.044         182.044        182.044         </param>
        <param name="fullscalePWM">            3360            3360             3360            3360            </param>
        <param name="ampsToSensor">            1000.0          1000.0           1000.0          1000.0          </param>
        <param name="Gearbox_M2J">              100               159             159            256            </param>
        <param name="Gearbox_E2J">   	          1               1                 1              1            </param>
        <param name="useMotorSpeedFbk">           1               1                 1              1            </param>
        <param name="MotorType">                "DC"             "DC"              "DC"           "DC"          </param>
        <param name="Verbose">                  0                                                               </param>
    </group>
    
    <group name="LIMITS">
        <param name="hardwareJntPosMax">         90          30             35             60          </param>
        <param name="hardwareJntPosMin">        -90         -80            -15             10          </param> 
        <param name="rotorPosMax">              0           0               0              0           </param>
        <param name="rotorPosMin">              0           0               0              0           </param> 
    </group>

    <group name="COUPLINGS"> 
                
        <param name ="matrixJ2M"> 
            1.000   0.000   0.000   0.000
            0.000   1.000   0.000   0.000
            0.000  -1.000  +1.000   0.000
            0.000   0.000   0.000   1.000   
        </param>
           
        <param name ="matrixM2J"> 
            1.000   0.000   0.000   0.000
            0.000   1.000  +1.000   0.000
            0.000   0.000  +1.000   0.000
            0.000   0.000   0.000   1.000   
        </param>

        <param name ="matrixE2J">  
            1.000   0.000   0.000   0.000   0.000   0.000
            0.000   1.000   0.000   0.000   0.000   0.000
            0.000   0.000   1.000   0.000   0.000   0.000
            0.000   0.000   0.000   1.000   0.000   0.000   
        </param>
                
    </group>      

    <group name="JOINTSET_CFG"> 
        <param name= "numberofsets"> 3</param>
         <group name="JOINTSET_0">
                    <param name="listofjoints">  0             </param>
                    <param name="constraint">    none          </param>
                    <param name="param1">        0             </param>
                    <param name="param2">        0             </param>
            </group> 
            <group name="JOINTSET_1">
                    <param name="listofjoints">   1 2           </param>
                    <param name="constraint">     none          </param>
                    <param name="param1">         0             </param>
                    <param name="param2">         0             </param>
            </group> 
            <group name="JOINTSET_2">
                    <param name="listofjoints">   3             </param>
                    <param name="constraint">     none          </param>
                    <param name="param1">         0             </param>
                    <param name="param2">         0             </param>
            </group> 
    </group>              
</params>
