<?xml version="1.0" encoding="UTF-8" ?>    

<devices>
    <device name="ikartLaser" type="rpLidar">  

    <group name="GENERAL">
    <param name="name">      ikart_laser        </param>
    <param name="max_angle">  180 </param>
    <param name="min_angle">  -180   </param>
    <param name="resolution">  1   </param>
    <param_name="motor_control"> 1 </param>
    <param_name="scan_type"> normal </param>
    <param name="clip_max">  3.5 </param>
    <param name="clip_min">  0.1 </param>
    <param name="allow_infinity">  1 </param>
    <param name="Serial_Configuration">  serial.ini </param>
    </group>

    </device>
</devices>

 
 
 
 
 
 
 
 
 
 
 
 
 
 
 
 
 
 
 
 
 
